{
  "data": [
    {
      "number": 1,
      "name": "سُورَةُ ٱلْفَاتِحَةِ",
      "shortName": "الفاتحة",
      "englishName": "Al-Faatiha",
      "englishNameTranslation": "The Opening",
      "numberOfAyahs": 7,
      "revelationType": "Meccan",
      "revelationOrder": 5
    },
    {
      "number": 2,
      "name": "سُورَةُ البَقَرَةِ",
      "shortName": "البقرة",
      "englishName": "Al-Baqara",
      "englishNameTranslation": "The Cow",
      "numberOfAyahs": 286,
      "revelationType": "Medinan",
      "revelationOrder": 87
    },
    {
      "number": 3,
      "name": "سُورَةُ آلِ عِمۡرَانَ",
      "shortName": "آل عمران",
      "englishName": "Aal-i-Imraan",
      "englishNameTranslation": "The Family of Imraan",
      "numberOfAyahs": 200,
      "revelationType": "Medinan",
      "revelationOrder": 89
    },
    {
      "number": 4,
      "name": "سُورَةُ النِّسَاءِ",
      "shortName": "النساء",
      "englishName": "An-Nisaa",
      "englishNameTranslation": "The Women",
      "numberOfAyahs": 176,
      "revelationType": "Medinan",
      "revelationOrder": 92
    },
    {
      "number": 5,
      "name": "سُورَةُ المَائـِدَةِ",
      "shortName": "المائدة",
      "englishName": "Al-Maaida",
      "englishNameTranslation": "The Table",
      "numberOfAyahs": 120,
      "revelationType": "Medinan",
      "revelationOrder": 112
    },
    {
      "number": 6,
      "name": "سُورَةُ الأَنۡعَامِ",
      "shortName": "الأنعام",
      "englishName": "Al-An'aam",
      "englishNameTranslation": "The Cattle",
      "numberOfAyahs": 165,
      "revelationType": "Meccan",
      "revelationOrder": 55
    },
    {
      "number": 7,
      "name": "سُورَةُ الأَعۡرَافِ",
      "shortName": "الأعراف",
      "englishName": "Al-A'raaf",
      "englishNameTranslation": "The Heights",
      "numberOfAyahs": 206,
      "revelationType": "Meccan",
      "revelationOrder": 39
    },
    {
      "number": 8,
      "name": "سُورَةُ الأَنفَالِ",
      "shortName": "الأنفال",
      "englishName": "Al-Anfaal",
      "englishNameTranslation": "The Spoils of War",
      "numberOfAyahs": 75,
      "revelationType": "Medinan",
      "revelationOrder": 88
    },
    {
      "number": 9,
      "name": "سُورَةُ التَّوۡبَةِ",
      "shortName": "التوبة",
      "englishName": "At-Tawba",
      "englishNameTranslation": "The Repentance",
      "numberOfAyahs": 129,
      "revelationType": "Medinan",
      "revelationOrder": 113
    },
    {
      "number": 10,
      "name": "سُورَةُ يُونُسَ",
      "shortName": "يونس",
      "englishName": "Yunus",
      "englishNameTranslation": "Jonas",
      "numberOfAyahs": 109,
      "revelationType": "Meccan",
      "revelationOrder": 51
    },
    {
      "number": 11,
      "name": "سُورَةُ هُودٍ",
      "shortName": "هود",
      "englishName": "Hud",
      "englishNameTranslation": "Hud",
      "numberOfAyahs": 123,
      "revelationType": "Meccan",
      "revelationOrder": 52
    },
    {
      "number": 12,
      "name": "سُورَةُ يُوسُفَ",
      "shortName": "يوسف",
      "englishName": "Yusuf",
      "englishNameTranslation": "Joseph",
      "numberOfAyahs": 111,
      "revelationType": "Meccan",
      "revelationOrder": 53
    },
    {
      "number": 13,
      "name": "سُورَةُ الرَّعۡدِ",
      "shortName": "الرعد",
      "englishName": "Ar-Ra'd",
      "englishNameTranslation": "The Thunder",
      "numberOfAyahs": 43,
      "revelationType": "Medinan",
      "revelationOrder": 96
    },
    {
      "number": 14,
      "name": "سُورَةُ إِبۡرَاهِيمَ",
      "shortName": "إبراهيم",
      "englishName": "Ibrahim",
      "englishNameTranslation": "Abraham",
      "numberOfAyahs": 52,
      "revelationType": "Meccan",
      "revelationOrder": 72
    },
    {
      "number": 15,
      "name": "سُورَةُ الحِجۡرِ",
      "shortName": "الحجر",
      "englishName": "Al-Hijr",
      "englishNameTranslation": "The Rock",
      "numberOfAyahs": 99,
      "revelationType": "Meccan",
      "revelationOrder": 54
    },
    {
      "number": 16,
      "name": "سُورَةُ النَّحۡلِ",
      "shortName": "النحل",
      "englishName": "An-Nahl",
      "englishNameTranslation": "The Bee",
      "numberOfAyahs": 128,
      "revelationType": "Meccan",
      "revelationOrder": 70
    },
    {
      "number": 17,
      "name": "سُورَةُ الإِسۡرَاءِ",
      "shortName": "الإسراء",
      "englishName": "Al-Israa",
      "englishNameTranslation": "The Night Journey",
      "numberOfAyahs": 111,
      "revelationType": "Meccan",
      "revelationOrder": 50
    },
    {
      "number": 18,
      "name": "سُورَةُ الكَهۡفِ",
      "shortName": "الكهف",
      "englishName": "Al-Kahf",
      "englishNameTranslation": "The Cave",
      "numberOfAyahs": 110,
      "revelationType": "Meccan",
      "revelationOrder": 69
    },
    {
      "number": 19,
      "name": "سُورَةُ مَرۡيَمَ",
      "shortName": "مريم",
      "englishName": "Maryam",
      "englishNameTranslation": "Mary",
      "numberOfAyahs": 98,
      "revelationType": "Meccan",
      "revelationOrder": 44
    },
    {
      "number": 20,
      "name": "سُورَةُ طه",
      "shortName": "طه",
      "englishName": "Taa-Haa",
      "englishNameTranslation": "Taa-Haa",
      "numberOfAyahs": 135,
      "revelationType": "Meccan",
      "revelationOrder": 45
    },
    {
      "number": 21,
      "name": "سُورَةُ الأَنبِيَاءِ",
      "shortName": "الأنبياء",
      "englishName": "Al-Anbiyaa",
      "englishNameTranslation": "The Prophets",
      "numberOfAyahs": 112,
      "revelationType": "Meccan",
      "revelationOrder": 73
    },
    {
      "number": 22,
      "name": "سُورَةُ الحَجِّ",
      "shortName": "الحج",
      "englishName": "Al-Hajj",
      "englishNameTranslation": "The Pilgrimage",
      "numberOfAyahs": 78,
      "revelationType": "Medinan",
      "revelationOrder": 103
    },
    {
      "number": 23,
      "name": "سُورَةُ المُؤۡمِنُونَ",
      "shortName": "المؤمنون",
      "englishName": "Al-Muminoon",
      "englishNameTranslation": "The Believers",
      "numberOfAyahs": 118,
      "revelationType": "Meccan",
      "revelationOrder": 74
    },
    {
      "number": 24,
      "name": "سُورَةُ النُّورِ",
      "shortName": "النور",
      "englishName": "An-Noor",
      "englishNameTranslation": "The Light",
      "numberOfAyahs": 64,
      "revelationType": "Medinan",
      "revelationOrder": 102
    },
    {
      "number": 25,
      "name": "سُورَةُ الفُرۡقَانِ",
      "shortName": "الفرقان",
      "englishName": "Al-Furqaan",
      "englishNameTranslation": "The Criterion",
      "numberOfAyahs": 77,
      "revelationType": "Meccan",
      "revelationOrder": 42
    },
    {
      "number": 26,
      "name": "سُورَةُ الشُّعَرَاءِ",
      "shortName": "الشعراء",
      "englishName": "Ash-Shu'araa",
      "englishNameTranslation": "The Poets",
      "numberOfAyahs": 227,
      "revelationType": "Meccan",
      "revelationOrder": 47
    },
    {
      "number": 27,
      "name": "سُورَةُ النَّمۡلِ",
      "shortName": "النمل",
      "englishName": "An-Naml",
      "englishNameTranslation": "The Ant",
      "numberOfAyahs": 93,
      "revelationType": "Meccan",
      "revelationOrder": 48
    },
    {
      "number": 28,
      "name": "سُورَةُ القَصَصِ",
      "shortName": "القصص",
      "englishName": "Al-Qasas",
      "englishNameTranslation": "The Stories",
      "numberOfAyahs": 88,
      "revelationType": "Meccan",
      "revelationOrder": 49
    },
    {
      "number": 29,
      "name": "سُورَةُ العَنكَبُوتِ",
      "shortName": "العنكبوت",
      "englishName": "Al-Ankaboot",
      "englishNameTranslation": "The Spider",
      "numberOfAyahs": 69,
      "revelationType": "Meccan",
      "revelationOrder": 85
    },
    {
      "number": 30,
      "name": "سُورَةُ الرُّومِ",
      "shortName": "الروم",
      "englishName": "Ar-Room",
      "englishNameTranslation": "The Romans",
      "numberOfAyahs": 60,
      "revelationType": "Meccan",
      "revelationOrder": 84
    },
    {
      "number": 31,
      "name": "سُورَةُ لُقۡمَانَ",
      "shortName": "لقمان",
      "englishName": "Luqman",
      "englishNameTranslation": "Luqman",
      "numberOfAyahs": 34,
      "revelationType": "Meccan",
      "revelationOrder": 57
    },
    {
      "number": 32,
      "name": "سُورَةُ السَّجۡدَةِ",
      "shortName": "السجدة",
      "englishName": "As-Sajda",
      "englishNameTranslation": "The Prostration",
      "numberOfAyahs": 30,
      "revelationType": "Meccan",
      "revelationOrder": 75
    },
    {
      "number": 33,
      "name": "سُورَةُ الأَحۡزَابِ",
      "shortName": "الأحزاب",
      "englishName": "Al-Ahzaab",
      "englishNameTranslation": "The Clans",
      "numberOfAyahs": 73,
      "revelationType": "Medinan",
      "revelationOrder": 90
    },
    {
      "number": 34,
      "name": "سُورَةُ سَبَإٍ",
      "shortName": "سبإ",
      "englishName": "Saba",
      "englishNameTranslation": "Sheba",
      "numberOfAyahs": 54,
      "revelationType": "Meccan",
      "revelationOrder": 58
    },
    {
      "number": 35,
      "name": "سُورَةُ فَاطِرٍ",
      "shortName": "فاطر",
      "englishName": "Faatir",
      "englishNameTranslation": "The Originator",
      "numberOfAyahs": 45,
      "revelationType": "Meccan",
      "revelationOrder": 43
    },
    {
      "number": 36,
      "name": "سُورَةُ يسٓ",
      "shortName": "يس",
      "englishName": "Yaseen",
      "englishNameTranslation": "Yaseen",
      "numberOfAyahs": 83,
      "revelationType": "Meccan",
      "revelationOrder": 41
    },
    {
      "number": 37,
      "name": "سُورَةُ الصَّافَّاتِ",
      "shortName": "الصافات",
      "englishName": "As-Saaffaat",
      "englishNameTranslation": "Those drawn up in Ranks",
      "numberOfAyahs": 182,
      "revelationType": "Meccan",
      "revelationOrder": 56
    },
    {
      "number": 38,
      "name": "سُورَةُ صٓ",
      "shortName": "ص",
      "englishName": "Saad",
      "englishNameTranslation": "The letter Saad",
      "numberOfAyahs": 88,
      "revelationType": "Meccan",
      "revelationOrder": 38
    },
    {
      "number": 39,
      "name": "سُورَةُ الزُّمَرِ",
      "shortName": "الزمر",
      "englishName": "Az-Zumar",
      "englishNameTranslation": "The Groups",
      "numberOfAyahs": 75,
      "revelationType": "Meccan",
      "revelationOrder": 59
    },
    {
      "number": 40,
      "name": "سُورَةُ غَافِرٍ",
      "shortName": "غافر",
      "englishName": "Ghafir",
      "englishNameTranslation": "The Forgiver",
      "numberOfAyahs": 85,
      "revelationType": "Meccan",
      "revelationOrder": 60
    },
    {
      "number": 41,
      "name": "سُورَةُ فُصِّلَتۡ",
      "shortName": "فصلت",
      "englishName": "Fussilat",
      "englishNameTranslation": "Explained in detail",
      "numberOfAyahs": 54,
      "revelationType": "Meccan",
      "revelationOrder": 61
    },
    {
      "number": 42,
      "name": "سُورَةُ الشُّورَىٰ",
      "shortName": "الشورى",
      "englishName": "Ash-Shura",
      "englishNameTranslation": "Consultation",
      "numberOfAyahs": 53,
      "revelationType": "Meccan",
      "revelationOrder": 62
    },
    {
      "number": 43,
      "name": "سُورَةُ الزُّخۡرُفِ",
      "shortName": "الزخرف",
      "englishName": "Az-Zukhruf",
      "englishNameTranslation": "Ornaments of gold",
      "numberOfAyahs": 89,
      "revelationType": "Meccan",
      "revelationOrder": 63
    },
    {
      "number": 44,
      "name": "سُورَةُ الدُّخَانِ",
      "shortName": "الدخان",
      "englishName": "Ad-Dukhaan",
      "englishNameTranslation": "The Smoke",
      "numberOfAyahs": 59,
      "revelationType": "Meccan",
      "revelationOrder": 64
    },
    {
      "number": 45,
      "name": "سُورَةُ الجَاثِيَةِ",
      "shortName": "الجاثية",
      "englishName": "Al-Jaathiya",
      "englishNameTranslation": "Crouching",
      "numberOfAyahs": 37,
      "revelationType": "Meccan",
      "revelationOrder": 65
    },
    {
      "number": 46,
      "name": "سُورَةُ الأَحۡقَافِ",
      "shortName": "الأحقاف",
      "englishName": "Al-Ahqaf",
      "englishNameTranslation": "The Dunes",
      "numberOfAyahs": 35,
      "revelationType": "Meccan",
      "revelationOrder": 66
    },
    {
      "number": 47,
      "name": "سُورَةُ مُحَمَّدٍ",
      "shortName": "محمد",
      "englishName": "Muhammad",
      "englishNameTranslation": "Muhammad",
      "numberOfAyahs": 38,
      "revelationType": "Medinan",
      "revelationOrder": 95
    },
    {
      "number": 48,
      "name": "سُورَةُ الفَتۡحِ",
      "shortName": "الفتح",
      "englishName": "Al-Fath",
      "englishNameTranslation": "The Victory",
      "numberOfAyahs": 29,
      "revelationType": "Medinan",
      "revelationOrder": 111
    },
    {
      "number": 49,
      "name": "سُورَةُ الحُجُرَاتِ",
      "shortName": "الحجرات",
      "englishName": "Al-Hujuraat",
      "englishNameTranslation": "The Inner Apartments",
      "numberOfAyahs": 18,
      "revelationType": "Medinan",
      "revelationOrder": 106
    },
    {
      "number": 50,
      "name": "سُورَةُ قٓ",
      "shortName": "ق",
      "englishName": "Qaaf",
      "englishNameTranslation": "The letter Qaaf",
      "numberOfAyahs": 45,
      "revelationType": "Meccan",
      "revelationOrder": 34
    },
    {
      "number": 51,
      "name": "سُورَةُ الذَّارِيَاتِ",
      "shortName": "الذاريات",
      "englishName": "Adh-Dhaariyat",
      "englishNameTranslation": "The Winnowing Winds",
      "numberOfAyahs": 60,
      "revelationType": "Meccan",
      "revelationOrder": 67
    },
    {
      "number": 52,
      "name": "سُورَةُ الطُّورِ",
      "shortName": "الطور",
      "englishName": "At-Tur",
      "englishNameTranslation": "The Mount",
      "numberOfAyahs": 49,
      "revelationType": "Meccan",
      "revelationOrder": 76
    },
    {
      "number": 53,
      "name": "سُورَةُ النَّجۡمِ",
      "shortName": "النجم",
      "englishName": "An-Najm",
      "englishNameTranslation": "The Star",
      "numberOfAyahs": 62,
      "revelationType": "Meccan",
      "revelationOrder": 23
    },
    {
      "number": 54,
      "name": "سُورَةُ القَمَرِ",
      "shortName": "القمر",
      "englishName": "Al-Qamar",
      "englishNameTranslation": "The Moon",
      "numberOfAyahs": 55,
      "revelationType": "Meccan",
      "revelationOrder": 37
    },
    {
      "number": 55,
      "name": "سُورَةُ الرَّحۡمَٰن",
      "shortName": "الرحمن",
      "englishName": "Ar-Rahmaan",
      "englishNameTranslation": "The Beneficent",
      "numberOfAyahs": 78,
      "revelationType": "Medinan",
      "revelationOrder": 97
    },
    {
      "number": 56,
      "name": "سُورَةُ الوَاقِعَةِ",
      "shortName": "الواقعة",
      "englishName": "Al-Waaqia",
      "englishNameTranslation": "The Inevitable",
      "numberOfAyahs": 96,
      "revelationType": "Meccan",
      "revelationOrder": 46
    },
    {
      "number": 57,
      "name": "سُورَةُ الحَدِيدِ",
      "shortName": "الحديد",
      "englishName": "Al-Hadid",
      "englishNameTranslation": "The Iron",
      "numberOfAyahs": 29,
      "revelationType": "Medinan",
      "revelationOrder": 94
    },
    {
      "number": 58,
      "name": "سُورَةُ المُجَادلَةِ",
      "shortName": "المجادلة",
      "englishName": "Al-Mujaadila",
      "englishNameTranslation": "The Pleading Woman",
      "numberOfAyahs": 22,
      "revelationType": "Medinan",
      "revelationOrder": 105
    },
    {
      "number": 59,
      "name": "سُورَةُ الحَشۡرِ",
      "shortName": "الحشر",
      "englishName": "Al-Hashr",
      "englishNameTranslation": "The Exile",
      "numberOfAyahs": 24,
      "revelationType": "Medinan",
      "revelationOrder": 101
    },
    {
      "number": 60,
      "name": "سُورَةُ المُمۡتَحنَةِ",
      "shortName": "الممتحنة",
      "englishName": "Al-Mumtahana",
      "englishNameTranslation": "She that is to be examined",
      "numberOfAyahs": 13,
      "revelationType": "Medinan",
      "revelationOrder": 91
    },
    {
      "number": 61,
      "name": "سُورَةُ الصَّفِّ",
      "shortName": "الصف",
      "englishName": "As-Saff",
      "englishNameTranslation": "The Ranks",
      "numberOfAyahs": 14,
      "revelationType": "Medinan",
      "revelationOrder": 109
    },
    {
      "number": 62,
      "name": "سُورَةُ الجُمُعَةِ",
      "shortName": "الجمعة",
      "englishName": "Al-Jumu'a",
      "englishNameTranslation": "Friday",
      "numberOfAyahs": 11,
      "revelationType": "Medinan",
      "revelationOrder": 110
    },
    {
      "number": 63,
      "name": "سُورَةُ المُنَافِقُونَ",
      "shortName": "المنافقون",
      "englishName": "Al-Munaafiqoon",
      "englishNameTranslation": "The Hypocrites",
      "numberOfAyahs": 11,
      "revelationType": "Medinan",
      "revelationOrder": 104
    },
    {
      "number": 64,
      "name": "سُورَةُ التَّغَابُنِ",
      "shortName": "التغابن",
      "englishName": "At-Taghaabun",
      "englishNameTranslation": "Mutual Disillusion",
      "numberOfAyahs": 18,
      "revelationType": "Medinan",
      "revelationOrder": 108
    },
    {
      "number": 65,
      "name": "سُورَةُ الطَّلَاقِ",
      "shortName": "الطلاق",
      "englishName": "At-Talaaq",
      "englishNameTranslation": "Divorce",
      "numberOfAyahs": 12,
      "revelationType": "Medinan",
      "revelationOrder": 99
    },
    {
      "number": 66,
      "name": "سُورَةُ التَّحۡرِيمِ",
      "shortName": "التحريم",
      "englishName": "At-Tahrim",
      "englishNameTranslation": "The Prohibition",
      "numberOfAyahs": 12,
      "revelationType": "Medinan",
      "revelationOrder": 107
    },
    {
      "number": 67,
      "name": "سُورَةُ المُلۡكِ",
      "shortName": "الملك",
      "englishName": "Al-Mulk",
      "englishNameTranslation": "The Sovereignty",
      "numberOfAyahs": 30,
      "revelationType": "Meccan",
      "revelationOrder": 77
    },
    {
      "number": 68,
      "name": "سُورَةُ القَلَمِ",
      "shortName": "القلم",
      "englishName": "Al-Qalam",
      "englishNameTranslation": "The Pen",
      "numberOfAyahs": 52,
      "revelationType": "Meccan",
      "revelationOrder": 2
    },
    {
      "number": 69,
      "name": "سُورَةُ الحَاقَّةِ",
      "shortName": "الحاقة",
      "englishName": "Al-Haaqqa",
      "englishNameTranslation": "The Reality",
      "numberOfAyahs": 52,
      "revelationType": "Meccan",
      "revelationOrder": 78
    },
    {
      "number": 70,
      "name": "سُورَةُ المَعَارِجِ",
      "shortName": "المعارج",
      "englishName": "Al-Ma'aarij",
      "englishNameTranslation": "The Ascending Stairways",
      "numberOfAyahs": 44,
      "revelationType": "Meccan",
      "revelationOrder": 79
    },
    {
      "number": 71,
      "name": "سُورَةُ نُوحٍ",
      "shortName": "نوح",
      "englishName": "Nooh",
      "englishNameTranslation": "Noah",
      "numberOfAyahs": 28,
      "revelationType": "Meccan",
      "revelationOrder": 71
    },
    {
      "number": 72,
      "name": "سُورَةُ الجِنِّ",
      "shortName": "الجن",
      "englishName": "Al-Jinn",
      "englishNameTranslation": "The Jinn",
      "numberOfAyahs": 28,
      "revelationType": "Meccan",
      "revelationOrder": 40
    },
    {
      "number": 73,
      "name": "سُورَةُ المُزَّمِّلِ",
      "shortName": "المزمل",
      "englishName": "Al-Muzzammil",
      "englishNameTranslation": "The Enshrouded One",
      "numberOfAyahs": 20,
      "revelationType": "Meccan",
      "revelationOrder": 3
    },
    {
      "number": 74,
      "name": "سُورَةُ المُدَّثِّرِ",
      "shortName": "المدثر",
      "englishName": "Al-Muddaththir",
      "englishNameTranslation": "The Cloaked One",
      "numberOfAyahs": 56,
      "revelationType": "Meccan",
      "revelationOrder": 4
    },
    {
      "number": 75,
      "name": "سُورَةُ القِيَامَةِ",
      "shortName": "القيامة",
      "englishName": "Al-Qiyaama",
      "englishNameTranslation": "The Resurrection",
      "numberOfAyahs": 40,
      "revelationType": "Meccan",
      "revelationOrder": 31
    },
    {
      "number": 76,
      "name": "سُورَةُ الإِنسَانِ",
      "shortName": "الإنسان",
      "englishName": "Al-Insaan",
      "englishNameTranslation": "Man",
      "numberOfAyahs": 31,
      "revelationType": "Medinan",
      "revelationOrder": 98
    },
    {
      "number": 77,
      "name": "سُورَةُ المُرۡسَلَاتِ",
      "shortName": "المرسلات",
      "englishName": "Al-Mursalaat",
      "englishNameTranslation": "The Emissaries",
      "numberOfAyahs": 50,
      "revelationType": "Meccan",
      "revelationOrder": 33
    },
    {
      "number": 78,
      "name": "سُورَةُ النَّبَإِ",
      "shortName": "النبإ",
      "englishName": "An-Naba",
      "englishNameTranslation": "The Announcement",
      "numberOfAyahs": 40,
      "revelationType": "Meccan",
      "revelationOrder": 80
    },
    {
      "number": 79,
      "name": "سُورَةُ النَّازِعَاتِ",
      "shortName": "النازعات",
      "englishName": "An-Naazi'aat",
      "englishNameTranslation": "Those who drag forth",
      "numberOfAyahs": 46,
      "revelationType": "Meccan",
      "revelationOrder": 81
    },
    {
      "number": 80,
      "name": "سُورَةُ عَبَسَ",
      "shortName": "عبس",
      "englishName": "Abasa",
      "englishNameTranslation": "He frowned",
      "numberOfAyahs": 42,
      "revelationType": "Meccan",
      "revelationOrder": 24
    },
    {
      "number": 81,
      "name": "سُورَةُ التَّكۡوِيرِ",
      "shortName": "التكوير",
      "englishName": "At-Takwir",
      "englishNameTranslation": "The Overthrowing",
      "numberOfAyahs": 29,
      "revelationType": "Meccan",
      "revelationOrder": 7
    },
    {
      "number": 82,
      "name": "سُورَةُ الانفِطَارِ",
      "shortName": "الانفطار",
      "englishName": "Al-Infitaar",
      "englishNameTranslation": "The Cleaving",
      "numberOfAyahs": 19,
      "revelationType": "Meccan",
      "revelationOrder": 82
    },
    {
      "number": 83,
      "name": "سُورَةُ المُطَفِّفِينَ",
      "shortName": "المطففين",
      "englishName": "Al-Mutaffifin",
      "englishNameTranslation": "Defrauding",
      "numberOfAyahs": 36,
      "revelationType": "Meccan",
      "revelationOrder": 86
    },
    {
      "number": 84,
      "name": "سُورَةُ الانشِقَاقِ",
      "shortName": "الانشقاق",
      "englishName": "Al-Inshiqaaq",
      "englishNameTranslation": "The Splitting Open",
      "numberOfAyahs": 25,
      "revelationType": "Meccan",
      "revelationOrder": 83
    },
    {
      "number": 85,
      "name": "سُورَةُ البُرُوجِ",
      "shortName": "البروج",
      "englishName": "Al-Burooj",
      "englishNameTranslation": "The Constellations",
      "numberOfAyahs": 22,
      "revelationType": "Meccan",
      "revelationOrder": 27
    },
    {
      "number": 86,
      "name": "سُورَةُ الطَّارِقِ",
      "shortName": "الطارق",
      "englishName": "At-Taariq",
      "englishNameTranslation": "The Morning Star",
      "numberOfAyahs": 17,
      "revelationType": "Meccan",
      "revelationOrder": 36
    },
    {
      "number": 87,
      "name": "سُورَةُ الأَعۡلَىٰ",
      "shortName": "الأعلى",
      "englishName": "Al-A'laa",
      "englishNameTranslation": "The Most High",
      "numberOfAyahs": 19,
      "revelationType": "Meccan",
      "revelationOrder": 8
    },
    {
      "number": 88,
      "name": "سُورَةُ الغَاشِيَةِ",
      "shortName": "الغاشية",
      "englishName": "Al-Ghaashiya",
      "englishNameTranslation": "The Overwhelming",
      "numberOfAyahs": 26,
      "revelationType": "Meccan",
      "revelationOrder": 68
    },
    {
      "number": 89,
      "name": "سُورَةُ الفَجۡرِ",
      "shortName": "الفجر",
      "englishName": "Al-Fajr",
      "englishNameTranslation": "The Dawn",
      "numberOfAyahs": 30,
      "revelationType": "Meccan",
      "revelationOrder": 10
    },
    {
      "number": 90,
      "name": "سُورَةُ البَلَدِ",
      "shortName": "البلد",
      "englishName": "Al-Balad",
      "englishNameTranslation": "The City",
      "numberOfAyahs": 20,
      "revelationType": "Meccan",
      "revelationOrder": 35
    },
    {
      "number": 91,
      "name": "سُورَةُ الشَّمۡسِ",
      "shortName": "الشمس",
      "englishName": "Ash-Shams",
      "englishNameTranslation": "The Sun",
      "numberOfAyahs": 15,
      "revelationType": "Meccan",
      "revelationOrder": 26
    },
    {
      "number": 92,
      "name": "سُورَةُ اللَّيۡلِ",
      "shortName": "الليل",
      "englishName": "Al-Lail",
      "englishNameTranslation": "The Night",
      "numberOfAyahs": 21,
      "revelationType": "Meccan",
      "revelationOrder": 9
    },
    {
      "number": 93,
      "name": "سُورَةُ الضُّحَىٰ",
      "shortName": "الضحى",
      "englishName": "Ad-Dhuhaa",
      "englishNameTranslation": "The Morning Hours",
      "numberOfAyahs": 11,
      "revelationType": "Meccan",
      "revelationOrder": 11
    },
    {
      "number": 94,
      "name": "سُورَةُ الشَّرۡحِ",
      "shortName": "الشرح",
      "englishName": "Ash-Sharh",
      "englishNameTranslation": "The Consolation",
      "numberOfAyahs": 8,
      "revelationType": "Meccan",
      "revelationOrder": 12
    },
    {
      "number": 95,
      "name": "سُورَةُ التِّينِ",
      "shortName": "التين",
      "englishName": "At-Tin",
      "englishNameTranslation": "The Fig",
      "numberOfAyahs": 8,
      "revelationType": "Meccan",
      "revelationOrder": 28
    },
    {
      "number": 96,
      "name": "سُورَةُ العَلَقِ",
      "shortName": "العلق",
      "englishName": "Al-Alaq",
      "englishNameTranslation": "The Clot",
      "numberOfAyahs": 19,
      "revelationType": "Meccan",
      "revelationOrder": 1
    },
    {
      "number": 97,
      "name": "سُورَةُ القَدۡرِ",
      "shortName": "القدر",
      "englishName": "Al-Qadr",
      "englishNameTranslation": "The Power, Fate",
      "numberOfAyahs": 5,
      "revelationType": "Meccan",
      "revelationOrder": 25
    },
    {
      "number": 98,
      "name": "سُورَةُ البَيِّنَةِ",
      "shortName": "البينة",
      "englishName": "Al-Bayyina",
      "englishNameTranslation": "The Evidence",
      "numberOfAyahs": 8,
      "revelationType": "Medinan",
      "revelationOrder": 100
    },
    {
      "number": 99,
      "name": "سُورَةُ الزَّلۡزَلَةِ",
      "shortName": "الزلزلة",
      "englishName": "Az-Zalzala",
      "englishNameTranslation": "The Earthquake",
      "numberOfAyahs": 8,
      "revelationType": "Medinan",
      "revelationOrder": 93
    },
    {
      "number": 100,
      "name": "سُورَةُ العَادِيَاتِ",
      "shortName": "العاديات",
      "englishName": "Al-Aadiyaat",
      "englishNameTranslation": "The Chargers",
      "numberOfAyahs": 11,
      "revelationType": "Meccan",
      "revelationOrder": 14
    },
    {
      "number": 101,
      "name": "سُورَةُ القَارِعَةِ",
      "shortName": "القارعة",
      "englishName": "Al-Qaari'a",
      "englishNameTranslation": "The Calamity",
      "numberOfAyahs": 11,
      "revelationType": "Meccan",
      "revelationOrder": 30
    },
    {
      "number": 102,
      "name": "سُورَةُ التَّكَاثُرِ",
      "shortName": "التكاثر",
      "englishName": "At-Takaathur",
      "englishNameTranslation": "Competition",
      "numberOfAyahs": 8,
      "revelationType": "Meccan",
      "revelationOrder": 16
    },
    {
      "number": 103,
      "name": "سُورَةُ العَصۡرِ",
      "shortName": "العصر",
      "englishName": "Al-Asr",
      "englishNameTranslation": "The Declining Day, Epoch",
      "numberOfAyahs": 3,
      "revelationType": "Meccan",
      "revelationOrder": 13
    },
    {
      "number": 104,
      "name": "سُورَةُ الهُمَزَةِ",
      "shortName": "الهمزة",
      "englishName": "Al-Humaza",
      "englishNameTranslation": "The Traducer",
      "numberOfAyahs": 9,
      "revelationType": "Meccan",
      "revelationOrder": 32
    },
    {
      "number": 105,
      "name": "سُورَةُ الفِيلِ",
      "shortName": "الفيل",
      "englishName": "Al-Fil",
      "englishNameTranslation": "The Elephant",
      "numberOfAyahs": 5,
      "revelationType": "Meccan",
      "revelationOrder": 19
    },
    {
      "number": 106,
      "name": "سُورَةُ قُرَيۡشٍ",
      "shortName": "قريش",
      "englishName": "Quraish",
      "englishNameTranslation": "Quraysh",
      "numberOfAyahs": 4,
      "revelationType": "Meccan",
      "revelationOrder": 29
    },
    {
      "number": 107,
      "name": "سُورَةُ المَاعُونِ",
      "shortName": "الماعون",
      "englishName": "Al-Maa'un",
      "englishNameTranslation": "Almsgiving",
      "numberOfAyahs": 7,
      "revelationType": "Meccan",
      "revelationOrder": 17
    },
    {
      "number": 108,
      "name": "سُورَةُ الكَوۡثَرِ",
      "shortName": "الكوثر",
      "englishName": "Al-Kawthar",
      "englishNameTranslation": "Abundance",
      "numberOfAyahs": 3,
      "revelationType": "Meccan",
      "revelationOrder": 15
    },
    {
      "number": 109,
      "name": "سُورَةُ الكَافِرُونَ",
      "shortName": "الكافرون",
      "englishName": "Al-Kaafiroon",
      "englishNameTranslation": "The Disbelievers",
      "numberOfAyahs": 6,
      "revelationType": "Meccan",
      "revelationOrder": 18
    },
    {
      "number": 110,
      "name": "سُورَةُ النَّصۡرِ",
      "shortName": "النصر",
      "englishName": "An-Nasr",
      "englishNameTranslation": "Divine Support",
      "numberOfAyahs": 3,
      "revelationType": "Medinan",
      "revelationOrder": 114
    },
    {
      "number": 111,
      "name": "سُورَةُ المَسَدِ",
      "shortName": "المسد",
      "englishName": "Al-Masad",
      "englishNameTranslation": "The Palm Fibre",
      "numberOfAyahs": 5,
      "revelationType": "Meccan",
      "revelationOrder": 6
    },
    {
      "number": 112,
      "name": "سُورَةُ الإِخۡلَاصِ",
      "shortName": "الإخلاص",
      "englishName": "Al-Ikhlaas",
      "englishNameTranslation": "Sincerity",
      "numberOfAyahs": 4,
      "revelationType": "Meccan",
      "revelationOrder": 22
    },
    {
      "number": 113,
      "name": "سُورَةُ الفَلَقِ",
      "shortName": "الفلق",
      "englishName": "Al-Falaq",
      "englishNameTranslation": "The Dawn",
      "numberOfAyahs": 5,
      "revelationType": "Meccan",
      "revelationOrder": 20
    },
    {
      "number": 114,
      "name": "سُورَةُ النَّاسِ",
      "shortName": "الناس",
      "englishName": "An-Naas",
      "englishNameTranslation": "Mankind",
      "numberOfAyahs": 6,
      "revelationType": "Meccan",
      "revelationOrder": 21
    }
  ]
}
